objns.py
objns-1.1.0.dist-info/LICENSE
objns-1.1.0.dist-info/METADATA
objns-1.1.0.dist-info/WHEEL
objns-1.1.0.dist-info/top_level.txt
objns-1.1.0.dist-info/RECORD
