Metadata-Version: 2.1
Name: objns
Version: 1.1.0
Summary: Transform a Python dictionary into an object
Home-page: https://github.com/kuralabs/objns
Author: KuraLabs S.R.L
Author-email: info@kuralabs.io
Keywords: objns
Classifier: Development Status :: 4 - Beta
Classifier: Intended Audience :: Developers
Classifier: License :: OSI Approved :: Apache Software License
Classifier: Natural Language :: English
Classifier: Operating System :: POSIX :: Linux
Classifier: Programming Language :: Python :: 3
License-File: LICENSE
